invision/__init__.py
invision/here.py
invitest-0.0.0.2.dist-info/METADATA
invitest-0.0.0.2.dist-info/WHEEL
invitest-0.0.0.2.dist-info/top_level.txt
invitest-0.0.0.2.dist-info/RECORD
