Metadata-Version: 2.1
Name: invitest
Version: 0.0.0.2
Summary: Invision Test Package
Author: mathamp
Author-email: jwzz123123@gmail.com
License: MIT
Platform: UNKNOWN
Requires-Python: >=3
